link_prediction/__init__.py
link_prediction/datasets/__init__.py
link_prediction/datasets/figma.py
link_prediction/datasets/rico.py
link_prediction/models/__init__.py
link_prediction/models/download_layout_encoder.py
link_prediction/models/classification/__init__.py
link_prediction/models/classification/base.py
link_prediction/models/classification/layout/__init__.py
link_prediction/models/classification/layout/classification.py
link_prediction/models/classification/layout/layout_encoder.py
link_prediction/models/classification/layout/preprocessing.py
link_prediction/models/classification/layout/screen_layout.py
link_prediction/models/classification/layout/types.py
link_prediction/models/classification/text/__init__.py
link_prediction/models/classification/text/classification.py
link_prediction/models/classification/text/preprocessing.py
link_prediction/models/classification/text/types.py
link_prediction/models/classification/text_and_layout/__init__.py
link_prediction/models/classification/text_and_layout/classification.py
link_prediction/models/classification/text_and_layout/preprocessing.py
link_prediction/models/classification/text_and_layout/types.py
link_prediction/models/heuristics/__init__.py
link_prediction/models/heuristics/base.py
link_prediction/models/heuristics/label_text_similarity/__init__.py
link_prediction/models/heuristics/label_text_similarity/classification.py
link_prediction/models/heuristics/label_text_similarity/preprocessing.py
link_prediction/models/heuristics/label_text_similarity/types.py
link_prediction/models/heuristics/largest_text_elements_contain_label/__init__.py
link_prediction/models/heuristics/largest_text_elements_contain_label/classification.py
link_prediction/models/heuristics/largest_text_elements_contain_label/preprocessing.py
link_prediction/models/heuristics/page_contains_label/__init__.py
link_prediction/models/heuristics/page_contains_label/classification.py
link_prediction-1.0.8.dist-info/LICENSE
link_prediction-1.0.8.dist-info/METADATA
link_prediction-1.0.8.dist-info/WHEEL
link_prediction-1.0.8.dist-info/entry_points.txt
link_prediction-1.0.8.dist-info/top_level.txt
link_prediction-1.0.8.dist-info/RECORD
