Metadata-Version: 2.1
Name: link-prediction
Version: 1.0.8
Summary: Predict links between screens of smartphone applications
Author: Christoph A. Johns
Author-email: christoph.johns@aalto.fi
License-File: LICENSE
Requires-Dist: numpy
Requires-Dist: pandas
Requires-Dist: scikit-learn
Requires-Dist: scipy
Requires-Dist: tqdm
Requires-Dist: imbalanced-learn
Requires-Dist: sentence-transformers
Requires-Dist: torch
Requires-Dist: click
Requires-Dist: joblib
Requires-Dist: requests
